ckanext/essopendata_theme/plugin.py
essopendata_theme-0.0.1.dist-info/METADATA
essopendata_theme-0.0.1.dist-info/WHEEL
essopendata_theme-0.0.1.dist-info/entry_points.txt
essopendata_theme-0.0.1.dist-info/top_level.txt
essopendata_theme-0.0.1.dist-info/RECORD
