Metadata-Version: 2.4
Name: essopendata_theme
Version: 0.0.1
Summary: CKAN ESS Opendata
Author-email: Coopdevs <info@coopdevs.org>
Classifier: Programming Language :: Python :: 3
Classifier: Operating System :: OS Independent
